DeFCoM-1.0.1.data/scripts/predict.py
DeFCoM-1.0.1.data/scripts/train.py
DeFCoM-1.0.1.dist-info/DESCRIPTION.rst
DeFCoM-1.0.1.dist-info/METADATA
DeFCoM-1.0.1.dist-info/RECORD
DeFCoM-1.0.1.dist-info/WHEEL
DeFCoM-1.0.1.dist-info/dependency_links.txt
DeFCoM-1.0.1.dist-info/metadata.json
DeFCoM-1.0.1.dist-info/top_level.txt
defcom/__init__.py
defcom/alignment.py
defcom/features.py
defcom/genome.py
defcom/motif_sites.py
defcom/performance_stats.py
